mcp_as_a_judge/__init__.py
mcp_as_a_judge/models.py
mcp_as_a_judge/server.py
mcp_as_a_judge/core/__init__.py
mcp_as_a_judge/core/constants.py
mcp_as_a_judge/core/logging_config.py
mcp_as_a_judge/core/server_helpers.py
mcp_as_a_judge/db/__init__.py
mcp_as_a_judge/db/cleanup_service.py
mcp_as_a_judge/db/conversation_history_service.py
mcp_as_a_judge/db/db_config.py
mcp_as_a_judge/db/dynamic_token_limits.py
mcp_as_a_judge/db/factory.py
mcp_as_a_judge/db/interface.py
mcp_as_a_judge/db/token_utils.py
mcp_as_a_judge/db/providers/__init__.py
mcp_as_a_judge/db/providers/sqlite_provider.py
mcp_as_a_judge/elicitation/__init__.py
mcp_as_a_judge/elicitation/factory.py
mcp_as_a_judge/elicitation/fallback_provider.py
mcp_as_a_judge/elicitation/interface.py
mcp_as_a_judge/elicitation/mcp_provider.py
mcp_as_a_judge/llm/__init__.py
mcp_as_a_judge/llm/llm_client.py
mcp_as_a_judge/llm/llm_integration.py
mcp_as_a_judge/messaging/__init__.py
mcp_as_a_judge/messaging/converters.py
mcp_as_a_judge/messaging/factory.py
mcp_as_a_judge/messaging/interface.py
mcp_as_a_judge/messaging/llm_api_provider.py
mcp_as_a_judge/messaging/llm_provider.py
mcp_as_a_judge/messaging/mcp_sampling_provider.py
mcp_as_a_judge/models/__init__.py
mcp_as_a_judge/models/enhanced_responses.py
mcp_as_a_judge/models/task_metadata.py
mcp_as_a_judge/prompting/__init__.py
mcp_as_a_judge/prompting/loader.py
mcp_as_a_judge/prompts/shared/critical_tool_warnings.md
mcp_as_a_judge/prompts/shared/response_constraints.md
mcp_as_a_judge/prompts/shared/task_size_definitions.md
mcp_as_a_judge/prompts/shared/todo.md
mcp_as_a_judge/prompts/system/dynamic_schema.md
mcp_as_a_judge/prompts/system/judge_code_change.md
mcp_as_a_judge/prompts/system/judge_coding_plan.md
mcp_as_a_judge/prompts/system/judge_response_repair.md
mcp_as_a_judge/prompts/system/judge_testing_implementation.md
mcp_as_a_judge/prompts/system/research_aspects.md
mcp_as_a_judge/prompts/system/research_requirements_analysis.md
mcp_as_a_judge-0.5.0.dist-info/METADATA
mcp_as_a_judge-0.5.0.dist-info/WHEEL
mcp_as_a_judge-0.5.0.dist-info/entry_points.txt
mcp_as_a_judge-0.5.0.dist-info/licenses/LICENSE
mcp_as_a_judge-0.5.0.dist-info/RECORD
