Metadata-Version: 2.4
Name: mcp-as-a-judge
Version: 0.5.0
Summary: MCP as a Judge: a behavioral MCP that strengthens AI coding assistants via explicit LLM evaluations
Project-URL: Homepage, https://github.com/OtherVibes/mcp-as-a-judge
Project-URL: Repository, https://github.com/OtherVibes/mcp-as-a-judge
Project-URL: Issues, https://github.com/OtherVibes/mcp-as-a-judge/issues
Project-URL: Documentation, https://github.com/OtherVibes/mcp-as-a-judge#readme
Author: Zvi Fried
Maintainer: Zvi Fried
License: MIT
License-File: LICENSE
Keywords: ai,automation,best-practices,code-review,judge,mcp,model-context-protocol,software-engineering
Classifier: Development Status :: 4 - Beta
Classifier: Environment :: Console
Classifier: Intended Audience :: Developers
Classifier: License :: OSI Approved :: MIT License
Classifier: Operating System :: OS Independent
Classifier: Programming Language :: Python :: 3
Classifier: Programming Language :: Python :: 3.12
Classifier: Programming Language :: Python :: 3.13
Classifier: Topic :: Scientific/Engineering :: Artificial Intelligence
Classifier: Topic :: Software Development :: Code Generators
Classifier: Topic :: Software Development :: Libraries :: Python Modules
Classifier: Topic :: Software Development :: Quality Assurance
Classifier: Typing :: Typed
Requires-Python: >=3.12
Requires-Dist: jinja2>=3.1.0
Requires-Dist: litellm>=1.0.0
Requires-Dist: mcp[cli]>=1.13.0
Requires-Dist: pydantic>=2.0.0
Requires-Dist: sqlmodel>=0.0.24
Requires-Dist: tenacity>=9.1.2
